boto3form/__init__.py
boto3form/aws_ecr/__init__.py
boto3form/aws_ecr/ecr.py
boto3form/aws_s3/__init__.py
boto3form/aws_s3/s3.py
boto3form-0.0.2.dist-info/METADATA
boto3form-0.0.2.dist-info/WHEEL
boto3form-0.0.2.dist-info/top_level.txt
boto3form-0.0.2.dist-info/RECORD
