Metadata-Version: 2.1
Name: boto3form
Version: 0.0.2
Summary: Create and delete aws ecr repository using python boto3 like terraform 
Home-page: https://github.com/rukmalsenavirathne/aws_python_boto3
Author: Rukmal Senavirathne
Classifier: Programming Language :: Python :: 3
Classifier: License :: OSI Approved :: MIT License
Classifier: Operating System :: OS Independent
Requires-Python: >=3.6
Requires-Dist: boto3
